[
  {
    "round": 1,
    "phase": 1,
    "table": 1,
    "winner": "etim",
    "player1": "etim",
    "player2": "richardmarighetti"
  },
  {
    "round": 1,
    "phase": 1,
    "table": 2,
    "winner": "escriso",
    "player1": "escriso",
    "player2": "mlixandrao"
  },
  {
    "round": 1,
    "phase": 1,
    "table": 3,
    "winner": "machiny",
    "player1": "machiny",
    "player2": "wlessa"
  },
  {
    "round": 1,
    "phase": 1,
    "table": 4,
    "winner": "augustoprime",
    "player1": "augustoprime",
    "player2": "leotcgbr"
  },
  {
    "round": 1,
    "phase": 1,
    "table": 5,
    "winner": "amorimlgaa",
    "player1": "amorimlgaa",
    "player2": "eduardo96"
  },
  {
    "round": 1,
    "phase": 1,
    "table": 6,
    "winner": "eddiespfc",
    "player1": "digao332k",
    "player2": "eddiespfc"
  },
  {
    "round": 1,
    "phase": 1,
    "table": 7,
    "winner": "gills",
    "player1": "gills",
    "player2": "kadintcg"
  },
  {
    "round": 1,
    "phase": 1,
    "table": 8,
    "winner": "rikelmematos",
    "player1": "rikelmematos",
    "player2": "agnera420"
  },
  {
    "round": 1,
    "phase": 1,
    "table": 9,
    "winner": "niev",
    "player1": "pedropato",
    "player2": "niev"
  },
  {
    "round": 1,
    "phase": 1,
    "table": 10,
    "winner": "dhyogo",
    "player1": "dhyogo",
    "player2": "styll"
  },
  {
    "round": 1,
    "phase": 1,
    "table": 11,
    "winner": "dougz92",
    "player1": "ayolosss",
    "player2": "dougz92"
  },
  {
    "round": 1,
    "phase": 1,
    "table": 12,
    "winner": 0,
    "player1": "brbokao",
    "player2": "carlin_6"
  },
  {
    "round": 1,
    "phase": 1,
    "table": 13,
    "winner": "josuan",
    "player1": "shikamaru_br",
    "player2": "josuan"
  },
  {
    "round": 1,
    "phase": 1,
    "table": 14,
    "winner": "glione",
    "player1": "josepaulo",
    "player2": "glione"
  },
  {
    "round": 1,
    "phase": 1,
    "table": 15,
    "winner": "346correia",
    "player1": "346correia",
    "player2": "lukinhas934"
  },
  {
    "round": 1,
    "phase": 1,
    "table": 16,
    "winner": "bdobalde",
    "player1": "bdobalde",
    "player2": "grandeaj"
  },
  {
    "round": 1,
    "phase": 1,
    "table": 17,
    "winner": "ultralordoficial",
    "player1": "mouragbl",
    "player2": "ultralordoficial"
  },
  {
    "round": 1,
    "phase": 1,
    "table": 18,
    "winner": "khaiky",
    "player1": "isaiaslima",
    "player2": "khaiky"
  },
  {
    "round": 1,
    "phase": 1,
    "table": 19,
    "winner": "paidasarah",
    "player1": "paidasarah"
  },
  {
    "round": 2,
    "phase": 1,
    "table": 1,
    "winner": "amorimlgaa",
    "player1": "josuan",
    "player2": "amorimlgaa"
  },
  {
    "round": 2,
    "phase": 1,
    "table": 2,
    "winner": "ultralordoficial",
    "player1": "machiny",
    "player2": "ultralordoficial"
  },
  {
    "round": 2,
    "phase": 1,
    "table": 3,
    "winner": "bdobalde",
    "player1": "bdobalde",
    "player2": "niev"
  },
  {
    "round": 2,
    "phase": 1,
    "table": 4,
    "winner": "gills",
    "player1": "gills",
    "player2": "glione"
  },
  {
    "round": 2,
    "phase": 1,
    "table": 5,
    "winner": "khaiky",
    "player1": "khaiky",
    "player2": "augustoprime"
  },
  {
    "round": 2,
    "phase": 1,
    "table": 6,
    "winner": "dhyogo",
    "player1": "dhyogo",
    "player2": "etim"
  },
  {
    "round": 2,
    "phase": 1,
    "table": 7,
    "winner": "346correia",
    "player1": "escriso",
    "player2": "346correia"
  },
  {
    "round": 2,
    "phase": 1,
    "table": 8,
    "winner": "rikelmematos",
    "player1": "rikelmematos",
    "player2": "paidasarah"
  },
  {
    "round": 2,
    "phase": 1,
    "table": 9,
    "winner": "dougz92",
    "player1": "dougz92",
    "player2": "eddiespfc"
  },
  {
    "round": 2,
    "phase": 1,
    "table": 10,
    "winner": "josepaulo",
    "player1": "brbokao",
    "player2": "josepaulo"
  },
  {
    "round": 2,
    "phase": 1,
    "table": 11,
    "winner": "carlin_6",
    "player1": "carlin_6",
    "player2": "grandeaj"
  },
  {
    "round": 2,
    "phase": 1,
    "table": 12,
    "winner": "agnera420",
    "player1": "kadintcg",
    "player2": "agnera420"
  },
  {
    "round": 2,
    "phase": 1,
    "table": 13,
    "winner": "ayolosss",
    "player1": "leotcgbr",
    "player2": "ayolosss"
  },
  {
    "round": 2,
    "phase": 1,
    "table": 14,
    "winner": "isaiaslima",
    "player1": "isaiaslima",
    "player2": "mouragbl"
  },
  {
    "round": 2,
    "phase": 1,
    "table": 15,
    "winner": "styll",
    "player1": "styll",
    "player2": "digao332k"
  },
  {
    "round": 2,
    "phase": 1,
    "table": 16,
    "winner": "pedropato",
    "player1": "mlixandrao",
    "player2": "pedropato"
  },
  {
    "round": 2,
    "phase": 1,
    "table": 17,
    "winner": "eduardo96",
    "player1": "eduardo96",
    "player2": "lukinhas934"
  },
  {
    "round": 2,
    "phase": 1,
    "table": 18,
    "winner": "richardmarighetti",
    "player1": "richardmarighetti",
    "player2": "wlessa"
  },
  {
    "round": 2,
    "phase": 1,
    "table": 19,
    "winner": "shikamaru_br",
    "player1": "shikamaru_br"
  },
  {
    "round": 3,
    "phase": 1,
    "table": 1,
    "winner": "ultralordoficial",
    "player1": "dhyogo",
    "player2": "ultralordoficial"
  },
  {
    "round": 3,
    "phase": 1,
    "table": 2,
    "winner": "rikelmematos",
    "player1": "rikelmematos",
    "player2": "khaiky"
  },
  {
    "round": 3,
    "phase": 1,
    "table": 3,
    "winner": "bdobalde",
    "player1": "346correia",
    "player2": "bdobalde"
  },
  {
    "round": 3,
    "phase": 1,
    "table": 4,
    "winner": "gills",
    "player1": "dougz92",
    "player2": "gills"
  },
  {
    "round": 3,
    "phase": 1,
    "table": 5,
    "winner": "carlin_6",
    "player1": "amorimlgaa",
    "player2": "carlin_6"
  },
  {
    "round": 3,
    "phase": 1,
    "table": 6,
    "winner": "shikamaru_br",
    "player1": "augustoprime",
    "player2": "shikamaru_br"
  },
  {
    "round": 3,
    "phase": 1,
    "table": 7,
    "winner": "pedropato",
    "player1": "josuan",
    "player2": "pedropato"
  },
  {
    "round": 3,
    "phase": 1,
    "table": 8,
    "winner": "richardmarighetti",
    "player1": "eduardo96",
    "player2": "richardmarighetti"
  },
  {
    "round": 3,
    "phase": 1,
    "table": 9,
    "winner": "glione",
    "player1": "glione",
    "player2": "agnera420"
  },
  {
    "round": 3,
    "phase": 1,
    "table": 10,
    "winner": "isaiaslima",
    "player1": "machiny",
    "player2": "isaiaslima"
  },
  {
    "round": 3,
    "phase": 1,
    "table": 11,
    "winner": "eddiespfc",
    "player1": "eddiespfc",
    "player2": "paidasarah"
  },
  {
    "round": 3,
    "phase": 1,
    "table": 12,
    "winner": "escriso",
    "player1": "escriso",
    "player2": "etim"
  },
  {
    "round": 3,
    "phase": 1,
    "table": 13,
    "winner": "josepaulo",
    "player1": "styll",
    "player2": "josepaulo"
  },
  {
    "round": 3,
    "phase": 1,
    "table": 14,
    "winner": "ayolosss",
    "player1": "niev",
    "player2": "ayolosss"
  },
  {
    "round": 3,
    "phase": 1,
    "table": 15,
    "winner": "grandeaj",
    "player1": "brbokao",
    "player2": "grandeaj"
  },
  {
    "round": 3,
    "phase": 1,
    "table": 16,
    "winner": "lukinhas934",
    "player1": "lukinhas934",
    "player2": "mlixandrao"
  },
  {
    "round": 3,
    "phase": 1,
    "table": 17,
    "winner": "mouragbl",
    "player1": "mouragbl",
    "player2": "digao332k"
  },
  {
    "round": 3,
    "phase": 1,
    "table": 18,
    "winner": "wlessa",
    "player1": "kadintcg",
    "player2": "wlessa"
  },
  {
    "round": 3,
    "phase": 1,
    "table": 19,
    "winner": "leotcgbr",
    "player1": "leotcgbr"
  },
  {
    "round": 4,
    "phase": 1,
    "table": 1,
    "winner": "ultralordoficial",
    "player1": "bdobalde",
    "player2": "ultralordoficial"
  },
  {
    "round": 4,
    "phase": 1,
    "table": 2,
    "winner": "gills",
    "player1": "gills",
    "player2": "rikelmematos"
  },
  {
    "round": 4,
    "phase": 1,
    "table": 3,
    "winner": "carlin_6",
    "player1": "carlin_6",
    "player2": "josepaulo"
  },
  {
    "round": 4,
    "phase": 1,
    "table": 4,
    "winner": "dhyogo",
    "player1": "dhyogo",
    "player2": "escriso"
  },
  {
    "round": 4,
    "phase": 1,
    "table": 5,
    "winner": "shikamaru_br",
    "player1": "shikamaru_br",
    "player2": "eddiespfc"
  },
  {
    "round": 4,
    "phase": 1,
    "table": 6,
    "winner": "pedropato",
    "player1": "pedropato",
    "player2": "richardmarighetti"
  },
  {
    "round": 4,
    "phase": 1,
    "table": 7,
    "winner": "346correia",
    "player1": "khaiky",
    "player2": "346correia"
  },
  {
    "round": 4,
    "phase": 1,
    "table": 8,
    "winner": "isaiaslima",
    "player1": "ayolosss",
    "player2": "isaiaslima"
  },
  {
    "round": 4,
    "phase": 1,
    "table": 9,
    "winner": "glione",
    "player1": "glione",
    "player2": "amorimlgaa"
  },
  {
    "round": 4,
    "phase": 1,
    "table": 10,
    "winner": "dougz92",
    "player1": "dougz92",
    "player2": "leotcgbr"
  },
  {
    "round": 4,
    "phase": 1,
    "table": 11,
    "winner": "grandeaj",
    "player1": "grandeaj",
    "player2": "augustoprime"
  },
  {
    "round": 4,
    "phase": 1,
    "table": 12,
    "winner": "agnera420",
    "player1": "wlessa",
    "player2": "agnera420"
  },
  {
    "round": 4,
    "phase": 1,
    "table": 13,
    "winner": "niev",
    "player1": "lukinhas934",
    "player2": "niev"
  },
  {
    "round": 4,
    "phase": 1,
    "table": 14,
    "winner": "etim",
    "player1": "machiny",
    "player2": "etim"
  },
  {
    "round": 4,
    "phase": 1,
    "table": 15,
    "winner": "styll",
    "player1": "styll",
    "player2": "eduardo96"
  },
  {
    "round": 4,
    "phase": 1,
    "table": 16,
    "winner": "josuan",
    "player1": "paidasarah",
    "player2": "josuan"
  },
  {
    "round": 4,
    "phase": 1,
    "table": 17,
    "winner": "mouragbl",
    "player1": "mouragbl",
    "player2": "brbokao"
  },
  {
    "round": 4,
    "phase": 1,
    "table": 18,
    "winner": "mlixandrao",
    "player1": "digao332k",
    "player2": "mlixandrao"
  },
  {
    "round": 4,
    "phase": 1,
    "table": 19,
    "winner": "kadintcg",
    "player1": "kadintcg"
  },
  {
    "round": 5,
    "phase": 1,
    "table": 1,
    "winner": "gills",
    "player1": "ultralordoficial",
    "player2": "gills"
  },
  {
    "round": 5,
    "phase": 1,
    "table": 2,
    "winner": "dougz92",
    "player1": "carlin_6",
    "player2": "dougz92"
  },
  {
    "round": 5,
    "phase": 1,
    "table": 3,
    "winner": "shikamaru_br",
    "player1": "isaiaslima",
    "player2": "shikamaru_br"
  },
  {
    "round": 5,
    "phase": 1,
    "table": 4,
    "winner": "glione",
    "player1": "bdobalde",
    "player2": "glione"
  },
  {
    "round": 5,
    "phase": 1,
    "table": 5,
    "winner": "346correia",
    "player1": "346correia",
    "player2": "dhyogo"
  },
  {
    "round": 5,
    "phase": 1,
    "table": 6,
    "winner": "rikelmematos",
    "player1": "pedropato",
    "player2": "rikelmematos"
  },
  {
    "round": 5,
    "phase": 1,
    "table": 7,
    "winner": "ayolosss",
    "player1": "etim",
    "player2": "ayolosss"
  },
  {
    "round": 5,
    "phase": 1,
    "table": 8,
    "winner": "khaiky",
    "player1": "grandeaj",
    "player2": "khaiky"
  },
  {
    "round": 5,
    "phase": 1,
    "table": 9,
    "winner": "styll",
    "player1": "agnera420",
    "player2": "styll"
  },
  {
    "round": 5,
    "phase": 1,
    "table": 10,
    "winner": "richardmarighetti",
    "player1": "amorimlgaa",
    "player2": "richardmarighetti"
  },
  {
    "round": 5,
    "phase": 1,
    "table": 11,
    "winner": "josuan",
    "player1": "josepaulo",
    "player2": "josuan"
  },
  {
    "round": 5,
    "phase": 1,
    "table": 12,
    "winner": "niev",
    "player1": "mouragbl",
    "player2": "niev"
  },
  {
    "round": 5,
    "phase": 1,
    "table": 13,
    "winner": "eddiespfc",
    "player1": "eddiespfc",
    "player2": "escriso"
  },
  {
    "round": 5,
    "phase": 1,
    "table": 14,
    "winner": "machiny",
    "player1": "kadintcg",
    "player2": "machiny"
  },
  {
    "round": 5,
    "phase": 1,
    "table": 15,
    "winner": "wlessa",
    "player1": "lukinhas934",
    "player2": "wlessa"
  },
  {
    "round": 5,
    "phase": 1,
    "table": 16,
    "winner": "leotcgbr",
    "player1": "leotcgbr",
    "player2": "eduardo96"
  },
  {
    "round": 5,
    "phase": 1,
    "table": 17,
    "winner": "paidasarah",
    "player1": "augustoprime",
    "player2": "paidasarah"
  },
  {
    "round": 5,
    "phase": 1,
    "table": 18,
    "winner": 0,
    "player1": "mlixandrao",
    "player2": "brbokao"
  },
  {
    "round": 6,
    "phase": 1,
    "table": 1,
    "winner": "346correia",
    "player1": "gills",
    "player2": "346correia"
  },
  {
    "round": 6,
    "phase": 1,
    "table": 2,
    "winner": "ultralordoficial",
    "player1": "ultralordoficial",
    "player2": "shikamaru_br"
  },
  {
    "round": 6,
    "phase": 1,
    "table": 3,
    "winner": "rikelmematos",
    "player1": "glione",
    "player2": "rikelmematos"
  },
  {
    "round": 6,
    "phase": 1,
    "table": 4,
    "winner": "richardmarighetti",
    "player1": "dougz92",
    "player2": "richardmarighetti"
  },
  {
    "round": 6,
    "phase": 1,
    "table": 5,
    "winner": "carlin_6",
    "player1": "carlin_6",
    "player2": "niev"
  },
  {
    "round": 6,
    "phase": 1,
    "table": 6,
    "winner": "eddiespfc",
    "player1": "eddiespfc",
    "player2": "dhyogo"
  },
  {
    "round": 6,
    "phase": 1,
    "table": 7,
    "winner": "styll",
    "player1": "josuan",
    "player2": "styll"
  },
  {
    "round": 6,
    "phase": 1,
    "table": 8,
    "winner": "ayolosss",
    "player1": "ayolosss",
    "player2": "pedropato"
  },
  {
    "round": 6,
    "phase": 1,
    "table": 9,
    "winner": "bdobalde",
    "player1": "bdobalde",
    "player2": "isaiaslima"
  },
  {
    "round": 6,
    "phase": 1,
    "table": 10,
    "winner": "leotcgbr",
    "player1": "agnera420",
    "player2": "leotcgbr"
  },
  {
    "round": 6,
    "phase": 1,
    "table": 11,
    "winner": "wlessa",
    "player1": "wlessa",
    "player2": "grandeaj"
  },
  {
    "round": 6,
    "phase": 1,
    "table": 12,
    "winner": "josepaulo",
    "player1": "machiny",
    "player2": "josepaulo"
  },
  {
    "round": 6,
    "phase": 1,
    "table": 13,
    "winner": "escriso",
    "player1": "escriso",
    "player2": "mouragbl"
  },
  {
    "round": 6,
    "phase": 1,
    "table": 14,
    "winner": "amorimlgaa",
    "player1": "amorimlgaa",
    "player2": "paidasarah"
  },
  {
    "round": 6,
    "phase": 1,
    "table": 15,
    "winner": "khaiky",
    "player1": "khaiky",
    "player2": "etim"
  },
  {
    "round": 6,
    "phase": 1,
    "table": 16,
    "winner": "kadintcg",
    "player1": "mlixandrao",
    "player2": "kadintcg"
  },
  {
    "round": 6,
    "phase": 1,
    "table": 17,
    "winner": "augustoprime",
    "player1": "augustoprime",
    "player2": "eduardo96"
  },
  {
    "round": 6,
    "phase": 1,
    "table": 18,
    "winner": "brbokao",
    "player1": "brbokao"
  },
  {
    "round": 7,
    "phase": 1,
    "table": 1,
    "winner": "carlin_6",
    "player1": "gills",
    "player2": "carlin_6"
  },
  {
    "round": 7,
    "phase": 1,
    "table": 2,
    "winner": 0,
    "player1": "ultralordoficial",
    "player2": "346correia"
  },
  {
    "round": 7,
    "phase": 1,
    "table": 3,
    "winner": "rikelmematos",
    "player1": "rikelmematos",
    "player2": "eddiespfc"
  },
  {
    "round": 7,
    "phase": 1,
    "table": 4,
    "winner": "glione",
    "player1": "glione",
    "player2": "dougz92"
  },
  {
    "round": 7,
    "phase": 1,
    "table": 5,
    "winner": "ayolosss",
    "player1": "ayolosss",
    "player2": "khaiky"
  },
  {
    "round": 7,
    "phase": 1,
    "table": 6,
    "winner": "richardmarighetti",
    "player1": "shikamaru_br",
    "player2": "richardmarighetti"
  },
  {
    "round": 7,
    "phase": 1,
    "table": 7,
    "winner": "styll",
    "player1": "bdobalde",
    "player2": "styll"
  },
  {
    "round": 7,
    "phase": 1,
    "table": 8,
    "winner": "niev",
    "player1": "leotcgbr",
    "player2": "niev"
  },
  {
    "round": 7,
    "phase": 1,
    "table": 9,
    "winner": "isaiaslima",
    "player1": "amorimlgaa",
    "player2": "isaiaslima"
  },
  {
    "round": 7,
    "phase": 1,
    "table": 10,
    "winner": "dhyogo",
    "player1": "josuan",
    "player2": "dhyogo"
  },
  {
    "round": 7,
    "phase": 1,
    "table": 11,
    "winner": "pedropato",
    "player1": "pedropato",
    "player2": "josepaulo"
  },
  {
    "round": 7,
    "phase": 1,
    "table": 12,
    "winner": "wlessa",
    "player1": "wlessa",
    "player2": "escriso"
  },
  {
    "round": 7,
    "phase": 1,
    "table": 13,
    "winner": "grandeaj",
    "player1": "grandeaj",
    "player2": "paidasarah"
  },
  {
    "round": 7,
    "phase": 1,
    "table": 14,
    "winner": "kadintcg",
    "player1": "kadintcg",
    "player2": "augustoprime"
  },
  {
    "round": 7,
    "phase": 1,
    "table": 15,
    "winner": 0,
    "player1": "etim",
    "player2": "brbokao"
  },
  {
    "round": 7,
    "phase": 1,
    "table": 16,
    "winner": "mouragbl",
    "player1": "agnera420",
    "player2": "mouragbl"
  },
  {
    "round": 7,
    "phase": 1,
    "table": 17,
    "winner": "machiny",
    "player1": "machiny"
  },
  {
    "round": 8,
    "phase": 1,
    "table": 1,
    "winner": "346correia",
    "player1": "rikelmematos",
    "player2": "346correia"
  },
  {
    "round": 8,
    "phase": 1,
    "table": 2,
    "winner": "ultralordoficial",
    "player1": "carlin_6",
    "player2": "ultralordoficial"
  },
  {
    "round": 8,
    "phase": 1,
    "table": 3,
    "winner": "richardmarighetti",
    "player1": "gills",
    "player2": "richardmarighetti"
  },
  {
    "round": 8,
    "phase": 1,
    "table": 4,
    "winner": "ayolosss",
    "player1": "glione",
    "player2": "ayolosss"
  },
  {
    "round": 8,
    "phase": 1,
    "table": 5,
    "winner": "styll",
    "player1": "styll",
    "player2": "wlessa"
  },
  {
    "round": 8,
    "phase": 1,
    "table": 6,
    "winner": "eddiespfc",
    "player1": "eddiespfc",
    "player2": "pedropato"
  },
  {
    "round": 8,
    "phase": 1,
    "table": 7,
    "winner": "isaiaslima",
    "player1": "isaiaslima",
    "player2": "dhyogo"
  },
  {
    "round": 8,
    "phase": 1,
    "table": 8,
    "winner": "bdobalde",
    "player1": "bdobalde",
    "player2": "shikamaru_br"
  },
  {
    "round": 8,
    "phase": 1,
    "table": 9,
    "winner": "dougz92",
    "player1": "khaiky",
    "player2": "dougz92"
  },
  {
    "round": 8,
    "phase": 1,
    "table": 10,
    "winner": "niev",
    "player1": "niev",
    "player2": "kadintcg"
  },
  {
    "round": 8,
    "phase": 1,
    "table": 11,
    "winner": "leotcgbr",
    "player1": "leotcgbr",
    "player2": "machiny"
  },
  {
    "round": 8,
    "phase": 1,
    "table": 12,
    "winner": "josuan",
    "player1": "josuan",
    "player2": "grandeaj"
  },
  {
    "round": 8,
    "phase": 1,
    "table": 13,
    "winner": "escriso",
    "player1": "escriso",
    "player2": "amorimlgaa"
  },
  {
    "round": 8,
    "phase": 1,
    "table": 14,
    "winner": "mouragbl",
    "player1": "josepaulo",
    "player2": "mouragbl"
  },
  {
    "round": 8,
    "phase": 1,
    "table": 15,
    "winner": "paidasarah",
    "player1": "etim",
    "player2": "paidasarah"
  },
  {
    "round": 8,
    "phase": 1,
    "table": 16,
    "winner": "augustoprime",
    "player1": "brbokao",
    "player2": "augustoprime"
  },
  {
    "round": 8,
    "phase": 1,
    "table": 17,
    "winner": "agnera420",
    "player1": "agnera420"
  },
  {
    "round": 9,
    "phase": 1,
    "table": 1,
    "winner": "346correia",
    "player1": "346correia",
    "player2": "richardmarighetti"
  },
  {
    "round": 9,
    "phase": 1,
    "table": 2,
    "winner": "ultralordoficial",
    "player1": "ultralordoficial",
    "player2": "rikelmematos"
  },
  {
    "round": 9,
    "phase": 1,
    "table": 3,
    "winner": "ayolosss",
    "player1": "styll",
    "player2": "ayolosss"
  },
  {
    "round": 9,
    "phase": 1,
    "table": 4,
    "winner": "carlin_6",
    "player1": "carlin_6",
    "player2": "bdobalde"
  },
  {
    "round": 9,
    "phase": 1,
    "table": 5,
    "winner": "dougz92",
    "player1": "dougz92",
    "player2": "niev"
  },
  {
    "round": 9,
    "phase": 1,
    "table": 6,
    "winner": "gills",
    "player1": "gills",
    "player2": "eddiespfc"
  },
  {
    "round": 9,
    "phase": 1,
    "table": 7,
    "winner": 0,
    "player1": "isaiaslima",
    "player2": "glione"
  },
  {
    "round": 9,
    "phase": 1,
    "table": 8,
    "winner": "dhyogo",
    "player1": "dhyogo",
    "player2": "pedropato"
  },
  {
    "round": 9,
    "phase": 1,
    "table": 9,
    "winner": "josuan",
    "player1": "escriso",
    "player2": "josuan"
  },
  {
    "round": 9,
    "phase": 1,
    "table": 10,
    "winner": "leotcgbr",
    "player1": "shikamaru_br",
    "player2": "leotcgbr"
  },
  {
    "round": 9,
    "phase": 1,
    "table": 11,
    "winner": "khaiky",
    "player1": "khaiky",
    "player2": "wlessa"
  },
  {
    "round": 9,
    "phase": 1,
    "table": 12,
    "winner": "grandeaj",
    "player1": "mouragbl",
    "player2": "grandeaj"
  },
  {
    "round": 9,
    "phase": 1,
    "table": 13,
    "winner": "kadintcg",
    "player1": "kadintcg",
    "player2": "paidasarah"
  },
  {
    "round": 9,
    "phase": 1,
    "table": 14,
    "winner": "augustoprime",
    "player1": "machiny",
    "player2": "augustoprime"
  },
  {
    "round": 9,
    "phase": 1,
    "table": 15,
    "winner": "brbokao",
    "player1": "agnera420",
    "player2": "brbokao"
  },
  {
    "round": 9,
    "phase": 1,
    "table": 16,
    "winner": "amorimlgaa",
    "player1": "josepaulo",
    "player2": "amorimlgaa"
  },
  {
    "round": 9,
    "phase": 1,
    "table": 17,
    "winner": "etim",
    "player1": "etim"
  },
  {
    "round": 10,
    "phase": 1,
    "table": 1,
    "winner": 0,
    "player1": "346correia",
    "player2": "ayolosss"
  },
  {
    "round": 10,
    "phase": 1,
    "table": 2,
    "winner": "richardmarighetti",
    "player1": "ultralordoficial",
    "player2": "richardmarighetti"
  },
  {
    "round": 10,
    "phase": 1,
    "table": 3,
    "winner": 0,
    "player1": "carlin_6",
    "player2": "styll"
  },
  {
    "round": 10,
    "phase": 1,
    "table": 4,
    "winner": "isaiaslima",
    "player1": "gills",
    "player2": "isaiaslima"
  },
  {
    "round": 10,
    "phase": 1,
    "table": 5,
    "winner": 0,
    "player1": "dougz92",
    "player2": "rikelmematos"
  },
  {
    "round": 10,
    "phase": 1,
    "table": 6,
    "winner": 0,
    "player1": "glione",
    "player2": "dhyogo"
  },
  {
    "round": 10,
    "phase": 1,
    "table": 7,
    "winner": "khaiky",
    "player1": "niev",
    "player2": "khaiky"
  },
  {
    "round": 10,
    "phase": 1,
    "table": 8,
    "winner": 0,
    "player1": "eddiespfc",
    "player2": "leotcgbr"
  },
  {
    "round": 10,
    "phase": 1,
    "table": 9,
    "winner": "josuan",
    "player1": "josuan",
    "player2": "bdobalde"
  },
  {
    "round": 10,
    "phase": 1,
    "table": 10,
    "winner": "shikamaru_br",
    "player1": "shikamaru_br",
    "player2": "kadintcg"
  },
  {
    "round": 10,
    "phase": 1,
    "table": 11,
    "winner": "escriso",
    "player1": "escriso",
    "player2": "pedropato"
  },
  {
    "round": 10,
    "phase": 1,
    "table": 12,
    "winner": 0,
    "player1": "grandeaj",
    "player2": "amorimlgaa"
  },
  {
    "round": 10,
    "phase": 1,
    "table": 13,
    "winner": "augustoprime",
    "player1": "wlessa",
    "player2": "augustoprime"
  },
  {
    "round": 10,
    "phase": 1,
    "table": 14,
    "winner": "mouragbl",
    "player1": "mouragbl",
    "player2": "etim"
  },
  {
    "round": 10,
    "phase": 1,
    "table": 15,
    "winner": "josepaulo",
    "player1": "josepaulo",
    "player2": "paidasarah"
  },
  {
    "round": 10,
    "phase": 1,
    "table": 16,
    "winner": "machiny",
    "player1": "brbokao",
    "player2": "machiny"
  },
  {
    "round": 11,
    "phase": 2,
    "table": 1,
    "winner": "leotcgbr",
    "player1": "346correia",
    "player2": "leotcgbr"
  },
  {
    "round": 11,
    "phase": 2,
    "table": 2,
    "winner": "ultralordoficial",
    "player1": "ultralordoficial",
    "player2": "eddiespfc"
  },
  {
    "round": 11,
    "phase": 2,
    "table": 3,
    "winner": "dhyogo",
    "player1": "ayolosss",
    "player2": "dhyogo"
  },
  {
    "round": 11,
    "phase": 2,
    "table": 4,
    "winner": "glione",
    "player1": "richardmarighetti",
    "player2": "glione"
  },
  {
    "round": 11,
    "phase": 2,
    "table": 5,
    "winner": "carlin_6",
    "player1": "carlin_6",
    "player2": "josuan"
  },
  {
    "round": 11,
    "phase": 2,
    "table": 6,
    "winner": "dougz92",
    "player1": "dougz92",
    "player2": "khaiky"
  },
  {
    "round": 11,
    "phase": 2,
    "table": 7,
    "winner": "rikelmematos",
    "player1": "rikelmematos",
    "player2": "gills"
  },
  {
    "round": 11,
    "phase": 2,
    "table": 8,
    "winner": "isaiaslima",
    "player1": "isaiaslima",
    "player2": "styll"
  },
  {
    "round": 12,
    "phase": 2,
    "table": 1,
    "winner": "leotcgbr",
    "player1": "leotcgbr",
    "player2": "isaiaslima"
  },
  {
    "round": 12,
    "phase": 2,
    "table": 2,
    "winner": "rikelmematos",
    "player1": "ultralordoficial",
    "player2": "rikelmematos"
  },
  {
    "round": 12,
    "phase": 2,
    "table": 3,
    "winner": "dougz92",
    "player1": "dhyogo",
    "player2": "dougz92"
  },
  {
    "round": 12,
    "phase": 2,
    "table": 4,
    "winner": "carlin_6",
    "player1": "glione",
    "player2": "carlin_6"
  },
  {
    "round": 13,
    "phase": 2,
    "table": 1,
    "winner": "leotcgbr",
    "player1": "leotcgbr",
    "player2": "carlin_6"
  },
  {
    "round": 13,
    "phase": 2,
    "table": 2,
    "winner": "rikelmematos",
    "player1": "rikelmematos",
    "player2": "dougz92"
  },
  {
    "round": 14,
    "phase": 2,
    "table": 1,
    "winner": "leotcgbr",
    "player1": "leotcgbr",
    "player2": "rikelmematos"
  }
]