{
  "id": "69a906b36a05f00a8c4a480c",
  "game": "GUNDAM",
  "format": null,
  "name": "The Eagle's Nest S4W8.5 MSA Online Locals",
  "date": "2026-03-21T00:00:00.000Z",
  "players": 68,
  "organizer": {
    "id": 452,
    "name": "The Eagle's Nest"
  },
  "decklists": true,
  "isPublic": true,
  "isOnline": true,
  "phases": [
    {
      "phase": 1,
      "type": "SWISS",
      "rounds": 7,
      "mode": "BO1"
    },
    {
      "phase": 2,
      "type": "SINGLE_BRACKET",
      "rounds": 1,
      "mode": "BO3"
    }
  ]
}