{
  "id": "695eea46ba66621ba08b6cae",
  "game": "VGC",
  "format": "SVF",
  "name": "★ PKWorlds'26: Q. Sinnoh ★",
  "date": "2026-03-08T17:00:00.000Z",
  "players": 54,
  "organizer": {
    "id": 623,
    "name": "ProfessorKai’s Tournaments"
  },
  "platform": "SWITCH",
  "decklists": true,
  "isPublic": true,
  "isOnline": true,
  "phases": [
    {
      "phase": 1,
      "type": "SWISS",
      "rounds": 6,
      "mode": "BO3"
    },
    {
      "phase": 2,
      "type": "SINGLE_BRACKET",
      "rounds": 1,
      "mode": "BO3"
    }
  ]
}